<PAMDataset>
  <Metadata>
    <MDI key="DataType">Generic</MDI>
  </Metadata>
  <PAMRasterBand band="1">
    <Histograms>
      <HistItem>
        <HistMin>9.410083823269133e-10</HistMin>
        <HistMax>1.470363616943359</HistMax>
        <BucketCount>256</BucketCount>
        <IncludeOutOfRange>1</IncludeOutOfRange>
        <Approximate>0</Approximate>
        <HistCounts>1783|599|452|442|401|445|440|422|427|426|396|447|464|488|485|537|451|430|483|449|493|550|557|660|632|632|633|694|808|974|1175|710|592|601|471|500|400|446|374|447|399|456|397|405|376|340|335|339|356|366|364|385|359|387|326|375|311|298|270|285|263|299|288|301|272|254|245|244|283|258|284|286|234|308|203|316|222|249|248|237|246|220|270|241|287|246|300|225|205|197|186|175|198|196|210|229|220|186|176|194|264|240|248|264|252|210|220|223|188|187|148|183|153|148|178|155|174|167|191|175|227|249|255|212|173|165|169|151|176|148|174|188|228|149|179|123|168|134|151|160|170|182|166|192|185|191|215|141|177|123|146|121|163|111|157|146|149|166|170|200|162|143|143|130|131|130|132|141|139|134|154|173|160|223|113|142|104|108|133|108|123|125|130|142|130|178|162|210|124|120|110|99|101|117|104|115|118|129|131|145|173|167|130|109|108|94|102|93|115|111|108|137|130|161|157|122|97|98|95|95|99|106|116|133|164|137|109|99|91|97|98|105|115|148|138|101|101|80|100|100|118|156|88|104|85|98|129|109|91|95|127|75|111|17|25|1</HistCounts>
      </HistItem>
    </Histograms>
    <Metadata>
      <MDI key="RepresentationType">ATHEMATIC</MDI>
      <MDI key="STATISTICS_COVARIANCES">0.1633925938013597</MDI>
      <MDI key="STATISTICS_EXCLUDEDVALUES"></MDI>
      <MDI key="STATISTICS_MAXIMUM">1.4703636169434</MDI>
      <MDI key="STATISTICS_MEAN">0.49313631761093</MDI>
      <MDI key="STATISTICS_MINIMUM">9.4100838232691e-10</MDI>
      <MDI key="STATISTICS_SKIPFACTORX">1</MDI>
      <MDI key="STATISTICS_SKIPFACTORY">1</MDI>
      <MDI key="STATISTICS_STDDEV">0.40421849759921</MDI>
    </Metadata>
  </PAMRasterBand>
</PAMDataset>
