<PAMDataset>
  <PAMRasterBand band="1">
    <Histograms>
      <HistItem>
        <HistMin>0</HistMin>
        <HistMax>1</HistMax>
        <BucketCount>256</BucketCount>
        <IncludeOutOfRange>1</IncludeOutOfRange>
        <Approximate>0</Approximate>
        <HistCounts>10117|304|272|250|352|306|365|315|290|291|285|333|304|318|320|326|341|380|320|322|327|354|329|309|365|352|338|364|405|367|412|346|382|381|411|419|430|460|465|445|419|390|377|391|395|384|375|404|396|412|420|149|62|84|63|62|71|66|57|64|70|83|78|64|57|67|65|62|70|66|66|62|65|66|75|93|69|60|71|78|62|76|67|67|93|74|85|80|88|71|66|79|75|54|66|69|56|79|83|86|75|83|72|72|72|77|68|91|66|70|74|70|77|75|65|78|61|82|80|92|55|56|64|77|70|68|73|70|69|87|77|76|80|87|98|81|87|68|74|81|79|75|85|101|86|85|76|97|73|68|75|76|103|86|75|97|72|89|93|76|70|91|107|76|97|76|81|89|80|67|91|92|98|78|69|56|88|91|77|67|93|70|80|104|100|101|100|104|77|118|115|104|150|234|229|262|259|267|255|261|231|291|243|236|247|255|260|226|303|246|233|290|267|240|235|289|260|236|253|247|280|243|229|208|241|304|239|250|224|212|251|276|235|239|235|242|289|259|250|228|227|234|260|255|283|247|215|257|235|304|242|228|237|229|247|41429</HistCounts>
      </HistItem>
    </Histograms>
    <Metadata>
      <MDI key="RepresentationType">ATHEMATIC</MDI>
      <MDI key="STATISTICS_EXCLUDEDVALUES"></MDI>
      <MDI key="STATISTICS_MAXIMUM">1</MDI>
      <MDI key="STATISTICS_MEAN">0.64845403125381</MDI>
      <MDI key="STATISTICS_MINIMUM">0</MDI>
      <MDI key="STATISTICS_SKIPFACTORX">1</MDI>
      <MDI key="STATISTICS_SKIPFACTORY">1</MDI>
      <MDI key="STATISTICS_STDDEV">0.4094908892654</MDI>
    </Metadata>
  </PAMRasterBand>
</PAMDataset>
