<PAMDataset>
  <PAMRasterBand band="1">
    <Histograms>
      <HistItem>
        <HistMin>0.5000201463699341</HistMin>
        <HistMax>1</HistMax>
        <BucketCount>256</BucketCount>
        <IncludeOutOfRange>1</IncludeOutOfRange>
        <Approximate>0</Approximate>
        <HistCounts>60|59|52|83|62|53|52|40|63|59|92|146|98|115|133|137|141|128|87|114|126|100|128|111|102|113|145|122|89|133|141|112|108|124|149|155|120|129|122|130|115|112|116|123|135|107|137|118|134|118|132|122|134|157|163|120|128|152|89|119|146|123|111|131|156|111|122|159|122|127|148|140|176|141|118|134|138|104|156|112|143|146|126|114|176|133|117|177|159|142|151|137|123|136|125|159|127|135|153|146|124|175|163|163|153|140|127|128|158|139|138|157|138|74|61|66|47|62|45|64|76|77|67|72|48|32|48|61|47|65|69|38|52|56|45|70|43|68|56|56|67|50|42|65|63|63|61|70|56|59|65|71|84|62|66|68|45|71|47|47|59|46|80|49|64|59|44|62|68|49|70|75|47|71|48|72|75|58|78|50|80|93|59|83|35|82|51|67|65|36|74|55|77|54|60|62|68|67|62|50|69|83|70|55|74|71|56|91|106|59|65|74|53|63|83|48|61|74|55|69|71|68|62|60|68|76|84|58|67|68|92|85|84|73|78|68|80|56|62|62|72|81|68|51|62|84|86|61|66|60|90|90|74|82|102|15113</HistCounts>
      </HistItem>
    </Histograms>
    <Metadata>
      <MDI key="RepresentationType">ATHEMATIC</MDI>
      <MDI key="STATISTICS_EXCLUDEDVALUES"></MDI>
      <MDI key="STATISTICS_MAXIMUM">1</MDI>
      <MDI key="STATISTICS_MEAN">0.82786052569498</MDI>
      <MDI key="STATISTICS_MINIMUM">0.50002014636993</MDI>
      <MDI key="STATISTICS_SKIPFACTORX">1</MDI>
      <MDI key="STATISTICS_SKIPFACTORY">1</MDI>
      <MDI key="STATISTICS_STDDEV">0.17576730312509</MDI>
    </Metadata>
  </PAMRasterBand>
</PAMDataset>
