<PAMDataset>
  <PAMRasterBand band="1">
    <Histograms>
      <HistItem>
        <HistMin>0.5000011324882507</HistMin>
        <HistMax>0.8501142263412476</HistMax>
        <BucketCount>256</BucketCount>
        <IncludeOutOfRange>1</IncludeOutOfRange>
        <Approximate>0</Approximate>
        <HistCounts>186|166|177|178|151|168|173|202|210|218|205|224|190|192|181|214|224|173|213|207|207|212|179|203|218|206|222|209|216|226|229|210|232|191|206|149|135|148|138|128|138|117|122|144|140|156|139|132|135|138|138|130|162|134|147|136|133|121|130|159|178|148|124|166|140|145|157|163|126|149|114|150|137|143|169|140|141|131|164|124|127|145|152|155|136|143|105|134|149|143|169|158|167|139|154|176|156|161|142|141|157|168|158|144|150|141|153|151|154|138|125|125|122|147|142|140|144|113|134|122|137|141|140|151|162|143|179|163|128|159|146|180|156|160|169|163|160|140|144|154|126|134|165|118|112|146|160|149|152|126|132|122|142|161|142|134|158|134|140|166|148|156|151|162|142|124|146|129|150|148|136|162|156|131|131|154|121|157|139|172|141|142|105|120|94|121|125|101|135|123|129|134|113|123|140|129|139|122|130|118|115|128|111|126|139|136|128|123|133|136|154|109|115|129|104|118|129|128|119|118|153|143|120|146|183|174|143|136|165|147|149|165|170|156|157|140|166|164|197|169|139|244|247|272|246|282|274|311|316|322|354|367|367|433|397|417</HistCounts>
      </HistItem>
    </Histograms>
    <Metadata>
      <MDI key="RepresentationType">ATHEMATIC</MDI>
      <MDI key="STATISTICS_EXCLUDEDVALUES"></MDI>
      <MDI key="STATISTICS_MAXIMUM">0.85011422634125</MDI>
      <MDI key="STATISTICS_MEAN">0.67819041091347</MDI>
      <MDI key="STATISTICS_MINIMUM">0.50000113248825</MDI>
      <MDI key="STATISTICS_SKIPFACTORX">1</MDI>
      <MDI key="STATISTICS_SKIPFACTORY">1</MDI>
      <MDI key="STATISTICS_STDDEV">0.10933888291514</MDI>
    </Metadata>
  </PAMRasterBand>
</PAMDataset>
