<PAMDataset>
  <PAMRasterBand band="1">
    <Histograms>
      <HistItem>
        <HistMin>0</HistMin>
        <HistMax>1</HistMax>
        <BucketCount>256</BucketCount>
        <IncludeOutOfRange>1</IncludeOutOfRange>
        <Approximate>0</Approximate>
        <HistCounts>14655|209|182|188|236|265|229|191|189|180|211|227|223|209|221|237|252|251|216|247|300|291|269|240|357|244|219|246|315|249|322|323|376|445|443|510|398|347|311|320|274|282|299|293|226|238|216|240|233|208|247|247|214|194|202|194|197|203|199|184|204|184|209|220|142|143|210|137|165|156|158|205|178|152|153|177|169|175|168|196|203|149|178|193|164|146|153|163|149|168|156|131|174|131|150|132|186|160|153|176|141|175|143|171|165|192|126|151|149|171|150|136|170|138|134|123|129|140|129|113|139|139|137|118|119|153|140|151|291|335|319|326|339|349|304|360|290|326|358|267|310|299|323|341|328|361|267|262|236|276|250|256|289|242|221|241|353|268|301|339|279|292|281|214|218|231|199|204|217|201|237|261|249|351|234|214|245|237|179|228|224|285|192|171|217|201|192|209|227|224|227|268|222|207|181|195|196|148|202|175|208|218|226|203|173|175|191|165|180|176|190|205|218|213|146|167|190|138|151|175|162|176|199|235|190|141|162|169|131|143|150|150|165|180|227|166|131|151|155|130|137|143|151|166|221|149|122|142|145|122|139|153|176|191|115|2875</HistCounts>
      </HistItem>
    </Histograms>
    <Metadata>
      <MDI key="RepresentationType">ATHEMATIC</MDI>
      <MDI key="STATISTICS_EXCLUDEDVALUES"></MDI>
      <MDI key="STATISTICS_MAXIMUM">1</MDI>
      <MDI key="STATISTICS_MEAN">0.39819649741537</MDI>
      <MDI key="STATISTICS_MINIMUM">0</MDI>
      <MDI key="STATISTICS_SKIPFACTORX">1</MDI>
      <MDI key="STATISTICS_SKIPFACTORY">1</MDI>
      <MDI key="STATISTICS_STDDEV">0.33447930253697</MDI>
    </Metadata>
  </PAMRasterBand>
</PAMDataset>
