<PAMDataset>
  <PAMRasterBand band="1">
    <Histograms>
      <HistItem>
        <HistMin>0</HistMin>
        <HistMax>0.8501150012016296</HistMax>
        <BucketCount>256</BucketCount>
        <IncludeOutOfRange>1</IncludeOutOfRange>
        <Approximate>0</Approximate>
        <HistCounts>957|0|3|6|3|6|11|22|37|11|19|85|131|194|253|139|85|72|53|69|68|93|124|129|137|165|661|906|888|900|926|915|918|897|974|964|961|922|976|1005|906|1004|985|935|987|871|980|879|976|859|984|900|1004|970|1037|995|1056|714|645|727|727|671|686|833|908|851|897|894|854|885|930|880|852|976|881|863|988|880|825|653|745|673|692|640|657|765|802|790|780|779|822|780|774|740|874|806|809|821|731|579|585|615|557|559|501|517|568|604|548|542|519|560|556|600|569|638|565|607|603|644|629|653|712|709|660|692|643|551|490|541|594|543|558|529|534|509|516|494|464|453|484|418|421|433|427|436|415|403|454|403|439|447|480|514|525|519|480|469|507|502|487|515|518|517|410|347|336|384|342|319|378|372|367|377|386|329|413|422|369|394|438|393|385|399|417|367|413|411|361|407|408|441|398|407|337|370|328|331|343|350|354|352|329|372|374|354|371|351|410|306|384|335|397|369|356|345|346|343|412|421|367|402|389|398|381|354|326|333|312|316|324|348|333|319|340|334|341|322|324|357|364|351|357|343|399|321|361|368|418|763|830|797|765|866|930|1</HistCounts>
      </HistItem>
    </Histograms>
    <Metadata>
      <MDI key="RepresentationType">ATHEMATIC</MDI>
      <MDI key="STATISTICS_EXCLUDEDVALUES"></MDI>
      <MDI key="STATISTICS_MAXIMUM">0.85011500120163</MDI>
      <MDI key="STATISTICS_MEAN">0.39207035224894</MDI>
      <MDI key="STATISTICS_MINIMUM">0</MDI>
      <MDI key="STATISTICS_SKIPFACTORX">1</MDI>
      <MDI key="STATISTICS_SKIPFACTORY">1</MDI>
      <MDI key="STATISTICS_STDDEV">0.22613249246958</MDI>
    </Metadata>
  </PAMRasterBand>
</PAMDataset>
