<PAMDataset>
  <PAMRasterBand band="1">
    <Histograms>
      <HistItem>
        <HistMin>0.5000260472297668</HistMin>
        <HistMax>1</HistMax>
        <BucketCount>256</BucketCount>
        <IncludeOutOfRange>1</IncludeOutOfRange>
        <Approximate>0</Approximate>
        <HistCounts>17|20|22|162|1571|385|180|131|99|73|80|92|58|43|38|41|693|1548|251|165|120|88|42|37|41|1297|984|247|150|120|90|54|40|1355|939|238|154|114|88|57|1868|504|223|144|101|72|1808|576|225|164|121|76|2112|339|197|157|340|1939|339|187|215|2141|339|198|1974|590|237|1986|592|1286|1337|2227|2416|2759|690|400|291|213|156|128|124|117|114|107|119|113|114|104|98|108|110|98|87|84|98|91|65|70|88|57|40|60|68|43|51|38|32|35|46|43|26|23|28|22|8|10|17|14|14|11|7|18|12|11|11|9|15|13|10|9|13|17|9|15|13|8|13|9|11|8|16|14|10|10|4|3|5|7|6|7|12|7|6|6|7|3|7|7|2|6|8|2|2|7|3|2|5|1|5|2|4|2|3|3|3|3|1|1|2|4|3|1|0|0|2|1|1|3|0|1|2|1|1|1|0|2|4|1|2|2|2|1|2|2|1|1|0|1|0|1|3|1|1|0|1|2|1|0|1|0|1|0|1|1|0|1|1|1|0|1|0|0|0|0|1|2|0|0|0|0|0|2|0|0|0|0|0|0|1|0|0|0|0|0|0|17</HistCounts>
      </HistItem>
    </Histograms>
    <Metadata>
      <MDI key="RepresentationType">ATHEMATIC</MDI>
      <MDI key="STATISTICS_EXCLUDEDVALUES"></MDI>
      <MDI key="STATISTICS_MAXIMUM">1</MDI>
      <MDI key="STATISTICS_MEAN">0.60644489353055</MDI>
      <MDI key="STATISTICS_MINIMUM">0.50002604722977</MDI>
      <MDI key="STATISTICS_SKIPFACTORX">1</MDI>
      <MDI key="STATISTICS_SKIPFACTORY">1</MDI>
      <MDI key="STATISTICS_STDDEV">0.049405903881542</MDI>
    </Metadata>
  </PAMRasterBand>
</PAMDataset>
