<PAMDataset>
  <PAMRasterBand band="1">
    <Histograms>
      <HistItem>
        <HistMin>0</HistMin>
        <HistMax>1</HistMax>
        <BucketCount>256</BucketCount>
        <IncludeOutOfRange>1</IncludeOutOfRange>
        <Approximate>0</Approximate>
        <HistCounts>18655|2064|460|211|220|209|187|194|168|2276|293|178|169|178|144|147|2123|366|153|154|145|123|136|2218|249|150|151|123|126|1171|1267|143|149|151|133|115|2033|414|133|147|150|131|43|34|1377|531|272|129|55|47|47|42|41|40|50|46|50|53|53|42|54|46|37|1060|809|341|133|51|55|51|51|46|46|52|52|61|72|62|57|681|1250|345|119|59|55|52|65|56|56|59|58|65|78|909|1061|331|115|60|52|38|45|40|45|39|44|44|40|43|51|48|1535|462|248|116|60|50|44|40|41|41|39|40|42|47|46|41|49|955|864|355|155|98|66|99|90|79|75|97|1363|910|207|113|110|110|82|94|1649|692|164|111|125|115|106|1604|747|175|114|112|132|130|2163|276|124|122|118|199|2158|267|130|124|126|1776|701|183|142|131|1792|694|174|173|155|2193|322|145|63|66|59|91|1554|482|287|135|70|68|62|67|62|60|1006|904|394|182|106|84|74|70|70|980|927|409|178|94|82|87|88|663|1250|435|197|99|91|79|81|1556|559|324|179|102|93|473|1348|493|241|130|102|649|1374|453|206|116|208|1745|470|234|147|1294|869|406|197|1013|1094|437|244|1832|589|23586</HistCounts>
      </HistItem>
    </Histograms>
    <Metadata>
      <MDI key="RepresentationType">ATHEMATIC</MDI>
      <MDI key="STATISTICS_EXCLUDEDVALUES"></MDI>
      <MDI key="STATISTICS_MAXIMUM">1</MDI>
      <MDI key="STATISTICS_MEAN">0.54999185144369</MDI>
      <MDI key="STATISTICS_MINIMUM">0</MDI>
      <MDI key="STATISTICS_SKIPFACTORX">1</MDI>
      <MDI key="STATISTICS_SKIPFACTORY">1</MDI>
      <MDI key="STATISTICS_STDDEV">0.38381180849544</MDI>
    </Metadata>
  </PAMRasterBand>
</PAMDataset>
