<PAMDataset>
  <PAMRasterBand band="1">
    <Histograms>
      <HistItem>
        <HistMin>0</HistMin>
        <HistMax>1</HistMax>
        <BucketCount>256</BucketCount>
        <IncludeOutOfRange>1</IncludeOutOfRange>
        <Approximate>0</Approximate>
        <HistCounts>6921|206|197|202|219|234|238|221|231|237|227|252|235|221|215|225|240|244|233|223|244|252|214|234|221|221|218|252|185|200|230|198|195|208|207|178|214|238|206|206|200|182|219|185|190|186|192|196|198|195|187|62|39|28|35|28|29|31|28|24|45|38|33|31|27|27|27|25|39|24|28|38|27|30|24|30|31|33|43|20|30|29|29|33|33|30|37|30|25|31|30|34|24|26|24|21|25|31|29|30|34|31|33|31|28|23|29|28|26|32|33|28|29|25|21|29|33|27|29|28|24|18|23|23|20|26|28|29|31|32|35|29|32|24|33|36|27|32|32|28|37|32|28|19|31|25|36|29|30|35|29|28|34|26|31|25|34|25|32|26|16|32|23|34|27|22|29|19|34|35|29|30|28|22|26|35|24|23|32|24|40|27|28|25|26|22|35|13|31|25|33|26|22|30|31|27|24|31|33|19|28|27|31|19|31|27|27|29|26|29|30|16|27|41|22|19|36|20|27|33|28|31|26|28|20|38|29|31|31|28|27|21|26|25|24|35|28|33|28|23|23|39|28|29|25|25|40|34|23|27|23|26|33|29|25|10740</HistCounts>
      </HistItem>
    </Histograms>
    <Metadata>
      <MDI key="RepresentationType">ATHEMATIC</MDI>
      <MDI key="STATISTICS_EXCLUDEDVALUES"></MDI>
      <MDI key="STATISTICS_MAXIMUM">1</MDI>
      <MDI key="STATISTICS_MEAN">0.44497184469327</MDI>
      <MDI key="STATISTICS_MINIMUM">0</MDI>
      <MDI key="STATISTICS_SKIPFACTORX">1</MDI>
      <MDI key="STATISTICS_SKIPFACTORY">1</MDI>
      <MDI key="STATISTICS_STDDEV">0.43352537363903</MDI>
    </Metadata>
  </PAMRasterBand>
</PAMDataset>
